fastzdp_upload/__init__.py
fastzdp_upload/model.py
fastzdp_upload/router.py
fastzdp_upload/util.py
fastzdp_upload-0.1.4.dist-info/LICENSE
fastzdp_upload-0.1.4.dist-info/METADATA
fastzdp_upload-0.1.4.dist-info/WHEEL
fastzdp_upload-0.1.4.dist-info/RECORD
