Metadata-Version: 2.1
Name: fastzdp-upload
Version: 0.1.4
Summary: 用于 FastAPI 快速实现文件上传下载功能
Author: zhangdapeng520
Author-email: 1156956636@qq.com
Requires-Python: >=3.12,<4.0
Classifier: Programming Language :: Python :: 3
Classifier: Programming Language :: Python :: 3.12
Requires-Dist: fastzdp-api (>=0.1.5,<0.2.0)
Requires-Dist: fastzdp-sqlmodel (>=0.1.4,<0.2.0)
Requires-Dist: python-multipart (>=0.0.12,<0.0.13)
